capydb/__init__.py
capydb/_client.py
capydb/_collection.py
capydb/_database.py
capydb/_emb_json/__init__.py
capydb/_emb_json/_emb_image.py
capydb/_emb_json/_emb_models.py
capydb/_emb_json/_emb_text.py
capydb/_emb_json/_vision_models.py
capydb/_types.py
capydb-0.7.0.dist-info/LICENSE
capydb-0.7.0.dist-info/METADATA
capydb-0.7.0.dist-info/WHEEL
capydb-0.7.0.dist-info/RECORD
