Metadata-Version: 2.3
Name: capydb
Version: 0.7.0
Summary: CapyDB Python Client
License: MIT
Author: Tomoh Kanazawa
Author-email: tomo@capydb.com
Requires-Python: >=3.9,<4.0
Classifier: License :: OSI Approved :: MIT License
Classifier: Programming Language :: Python :: 3
Classifier: Programming Language :: Python :: 3.9
Classifier: Programming Language :: Python :: 3.10
Classifier: Programming Language :: Python :: 3.11
Classifier: Programming Language :: Python :: 3.12
Classifier: Programming Language :: Python :: 3.13
Requires-Dist: pymongo (>=4.11.3,<5.0.0)
Requires-Dist: requests (>=2.32.3,<3.0.0)
Project-URL: Documentation, https://docs.capydb.com
Project-URL: Homepage, https://capydb.com
Project-URL: Repository, https://github.com/capydb/capydb-py
